solidity_audit_lib/__init__.py
solidity_audit_lib/encrypting.py
solidity_audit_lib/messaging.py
solidity_audit_lib/subtensor_wrapper.py
solidity_audit_lib/utils.py
solidity_audit_lib/relayer_client/__init__.py
solidity_audit_lib/relayer_client/client.py
solidity_audit_lib/relayer_client/relayer_types.py
solidity_audit_client-2508.27.1.dist-info/LICENSE
solidity_audit_client-2508.27.1.dist-info/METADATA
solidity_audit_client-2508.27.1.dist-info/WHEEL
solidity_audit_client-2508.27.1.dist-info/top_level.txt
solidity_audit_client-2508.27.1.dist-info/RECORD
