Metadata-Version: 2.1
Name: solidity-audit-client
Version: 2508.27.1
Summary: Solidity-Audit utility library
Home-page: https://github.com/ReinforcedAIAudits/lib
Author: https://github.com/ReinforcedAIAudits
Author-email: 
License: MIT
Classifier: Development Status :: 3 - Alpha
Classifier: Intended Audience :: Developers
Classifier: Topic :: Software Development :: Build Tools
Classifier: License :: OSI Approved :: MIT License
Classifier: Programming Language :: Python :: 3 :: Only
Classifier: Programming Language :: Python :: 3.8
Classifier: Programming Language :: Python :: 3.9
Classifier: Programming Language :: Python :: 3.10
Classifier: Topic :: Scientific/Engineering
Classifier: Topic :: Scientific/Engineering :: Mathematics
Classifier: Topic :: Scientific/Engineering :: Artificial Intelligence
Classifier: Topic :: Software Development
Classifier: Topic :: Software Development :: Libraries
Classifier: Topic :: Software Development :: Libraries :: Python Modules
Requires-Python: >=3.8
License-File: LICENSE
Requires-Dist: bittensor>=9.1.0
Requires-Dist: async-substrate-interface>=1.0.8
Requires-Dist: substrate-interface==1.7.11
Requires-Dist: sr25519-ecdh==0.1.0
Requires-Dist: bittensor-drand==1.0.0
